comparisonframe/.paa.config
comparisonframe/__init__.py
comparisonframe/comparisonframe.py
comparisonframe/lsts_package_versions.yml
comparisonframe/notebook.ipynb
comparisonframe/package_licenses.json
comparisonframe/package_mapping.json
comparisonframe/release_notes.md
comparisonframe/setup.py
comparisonframe/version_logs.csv
comparisonframe/mkdocs/mkdocs.yml
comparisonframe/mkdocs/docs/comparisonframe-flow.png
comparisonframe/mkdocs/docs/flow.md
comparisonframe/mkdocs/docs/index.md
comparisonframe/mkdocs/docs/release-notes.md
comparisonframe/mkdocs/docs/usage-examples.md
comparisonframe/mkdocs/docs/css/extra.css
comparisonframe/mkdocs/site/404.html
comparisonframe/mkdocs/site/comparisonframe-flow.png
comparisonframe/mkdocs/site/index.html
comparisonframe/mkdocs/site/sitemap.xml
comparisonframe/mkdocs/site/sitemap.xml.gz
comparisonframe/mkdocs/site/assets/images/favicon.png
comparisonframe/mkdocs/site/assets/javascripts/bundle.d6f25eb3.min.js
comparisonframe/mkdocs/site/assets/javascripts/bundle.d6f25eb3.min.js.map
comparisonframe/mkdocs/site/assets/javascripts/lunr/tinyseg.js
comparisonframe/mkdocs/site/assets/javascripts/lunr/wordcut.js
comparisonframe/mkdocs/site/assets/javascripts/lunr/min/lunr.ar.min.js
comparisonframe/mkdocs/site/assets/javascripts/lunr/min/lunr.da.min.js
comparisonframe/mkdocs/site/assets/javascripts/lunr/min/lunr.de.min.js
comparisonframe/mkdocs/site/assets/javascripts/lunr/min/lunr.du.min.js
comparisonframe/mkdocs/site/assets/javascripts/lunr/min/lunr.el.min.js
comparisonframe/mkdocs/site/assets/javascripts/lunr/min/lunr.es.min.js
comparisonframe/mkdocs/site/assets/javascripts/lunr/min/lunr.fi.min.js
comparisonframe/mkdocs/site/assets/javascripts/lunr/min/lunr.fr.min.js
comparisonframe/mkdocs/site/assets/javascripts/lunr/min/lunr.he.min.js
comparisonframe/mkdocs/site/assets/javascripts/lunr/min/lunr.hi.min.js
comparisonframe/mkdocs/site/assets/javascripts/lunr/min/lunr.hu.min.js
comparisonframe-0.0.5.dist-info/LICENSE
comparisonframe-0.0.5.dist-info/METADATA
comparisonframe-0.0.5.dist-info/WHEEL
comparisonframe-0.0.5.dist-info/top_level.txt
comparisonframe-0.0.5.dist-info/RECORD
