Metadata-Version: 2.1
Name: comparisonframe
Version: 0.0.5
Summary: A simple tool to compare textual data against validation sets.
Author: Kyrylo Mordan
Author-email: parachute.repo@gmail.com
License: mit
Keywords: ['aa-paa-tool']
Classifier: Development Status :: 3 - Alpha
Classifier: Intended Audience :: Developers
Classifier: Intended Audience :: Science/Research
Classifier: Programming Language :: Python :: 3
Classifier: Programming Language :: Python :: 3.9
Classifier: Programming Language :: Python :: 3.10
Classifier: Programming Language :: Python :: 3.11
Classifier: License :: OSI Approved :: MIT License
Classifier: Topic :: Scientific/Engineering
License-File: LICENSE
Requires-Dist: pandas>=2.1.1
Requires-Dist: mocker-db>=0.2.1
Requires-Dist: attrs>=22.1.0
Requires-Dist: numpy==1.26.0
